tinybones/__init__.py
tinybones/columns.py
tinybones/rows.py
tinybones/table.py
tinybones/value.py
tinybones-0.0.1.dist-info/METADATA
tinybones-0.0.1.dist-info/WHEEL
tinybones-0.0.1.dist-info/top_level.txt
tinybones-0.0.1.dist-info/RECORD
