Metadata-Version: 2.1
Name: tinybones
Version: 0.0.1
Summary: Pure Python data table backbones.
Home-page: https://github.com/eddiethedean/tinybones
Author: Odos Matthews
Author-email: odosmatthews@gmail.com
License: MIT
Classifier: License :: OSI Approved :: MIT License
Classifier: Programming Language :: Python :: 3
Classifier: Programming Language :: Python :: 3.6
Requires-Python: >=3.6
